sycret-0.2.8.dist-info/METADATA
sycret-0.2.8.dist-info/WHEEL
sycret/__init__.py
sycret/fss.py
sycret/utils.py
sycret/sycret/__init__.py
sycret/sycret/ffi.py
sycret/sycret/native.so
sycret-0.2.8.dist-info/RECORD
