Metadata-Version: 2.1
Name: sycret
Version: 0.2.8
Requires-Dist: numpy>=1
Requires-Dist: cffi>=1
Requires-Dist: pycparser>=2
Author: Pierre Tholoniat
Maintainer: Pierre Tholoniat
Maintainer-email: pierre@tholoniat.com
License: Apache-2.0
Requires-Python: >=3.6
Project-URL: Homepage, https://github.com/OpenMined/sycret
